pyvcg/__init__.py
pyvcg/graph.py
pyvcg/smt.py
pyvcg/vcg.py
pyvcg/version.py
pyvcg/driver/__init__.py
pyvcg/driver/cvc5_api.py
pyvcg/driver/cvc5_smtlib.py
pyvcg/driver/file_smtlib.py
pyvcg-1.0.10.dist-info/licenses/LICENSE
pyvcg-1.0.10.dist-info/METADATA
pyvcg-1.0.10.dist-info/WHEEL
pyvcg-1.0.10.dist-info/top_level.txt
pyvcg-1.0.10.dist-info/RECORD
