Metadata-Version: 2.4
Name: pyvcg
Version: 1.0.10
Summary: Verification Condition Generator
Home-page: https://github.com/florianschanda/PyVCG
Author: Florian Schanda
Author-email: florian@schanda.org.uk
License: GNU General Public License v3
Project-URL: Bug Tracker, https://github.com/florianschanda/PyVCG/issues
Project-URL: Documentation, https://github.com/pages/florianschanda/PyVCG/
Project-URL: Source Code, https://github.com/florianschanda/PyVCG
Classifier: Development Status :: 5 - Production/Stable
Classifier: Intended Audience :: Developers
Classifier: Intended Audience :: Science/Research
Classifier: License :: OSI Approved :: GNU General Public License v3 or later (GPLv3+)
Classifier: Operating System :: POSIX :: Linux
Classifier: Topic :: Scientific/Engineering :: Mathematics
Classifier: Topic :: Software Development :: Compilers
Requires-Python: >=3.8
License-File: LICENSE
Provides-Extra: api
Requires-Dist: cvc5==1.3.2; extra == "api"
Dynamic: author
Dynamic: author-email
Dynamic: classifier
Dynamic: description
Dynamic: description-content-type
Dynamic: home-page
Dynamic: license
Dynamic: license-file
Dynamic: project-url
Dynamic: provides-extra
Dynamic: requires-python
Dynamic: summary
